tests/__init__.py
tests/test_nlp.py
tests/test_preprocessing.py
tests/test_representation.py
tests/test_visualization.py
texthero/__init__.py
texthero/nlp.py
texthero/preprocessing.py
texthero/representation.py
texthero/stopwords.py
texthero/visualization.py
texthero-1.1.0.dist-info/LICENSE
texthero-1.1.0.dist-info/METADATA
texthero-1.1.0.dist-info/WHEEL
texthero-1.1.0.dist-info/top_level.txt
texthero-1.1.0.dist-info/RECORD
